{
    // Этот объект-индекс предназначен для мгновенного поиска userId
    // по различным идентификаторам во время входа в систему.
    // Он должен обновляться каждый раз, когда пользователь регистрируется
    // или привязывает новый способ входа.
  
      "380669061564": "uuid-1a2b3c-4d5e6f-7g8h9i",
      "380501234567": "uuid-manager-xyz-123",
      "telegram_id_sergey_sivoglaz": "uuid-1a2b3c-4d5e6f-7g8h9i",
      "telegram_id_pronkevich_dv": "uuid-manager-xyz-123",
      // Ключ - это providerId из объекта auth пользователя
      "109876543210987654321": "uuid-1a2b3c-4d5e6f-7g8h9i",
      // Ключ - это providerId из объекта auth пользователя
      "001234.a1b2c3d4e5f6.0123": "uuid-1a2b3c-4d5e6f-7g8h9i"
  }